{"type": "Feature", "id": 12523003, "geometry": {"type": "Point", "coordinates": [42.985802, 14.755]}, "properties": {"woe:id": 12523003, "woe:parent_id": 1958951, "woe:name": "Hodeidah Airport", "woe:placetype": 14, "woe:placetype_name": "Airport", "woe:lang": "ENG", "iso:country": "YE", "meta:provider": ["geoplanet:7.3.1", "geoplanet:7.3.2", "geoplanet:7.4.0", "geoplanet:7.4.1", "geoplanet:7.5.1", "geoplanet:7.5.2", "geoplanet:7.6.0", "geoplanet:7.8.1", "geoplanet:7.9.0", "geoplanet:7.10.0", "geoplanet:8.0.0", "woeplanet:8.0.0"], "meta:indexed": "2020-08-20T20:49:03.155593", "woe:alias_ENG_V": ["HOD Airport", "HOD"], "meta:updated": "2020-10-14T11:52:00.261549", "woe:hierarchy": {"continent": 24865671, "country": 23425002, "town": 0, "planet": 1, "county": 56189914, "suburb": 0, "state": 20070047, "region": 0, "localadmin": 0}, "woe:timezone_id": 28350806, "woe:hash": "sfwefnj61g35", "woe:centroid": [42.985802, 14.755], "geom:latitude": 14.755, "geom:longitude": 42.985802, "geom:hash": "sfwefnj61g35", "woe:latitude": 14.755, "geom:centroid": [42.985802, 14.755], "woe:longitude": 42.985802, "woe:repo": "woeplanet-airport-ye", "geom:area": 0.0, "woe:scale": 19}}