{"type": "Feature", "id": 12523001, "geometry": {"type": "Point", "coordinates": [46.8256, 14.5561]}, "properties": {"woe:id": 12523001, "woe:parent_id": 1959014, "woe:name": "Ataq Airport", "woe:placetype": 14, "woe:placetype_name": "Airport", "woe:lang": "ENG", "iso:country": "YE", "meta:provider": ["geoplanet:7.3.1", "geoplanet:7.3.2", "geoplanet:7.4.0", "geoplanet:7.4.1", "geoplanet:7.5.1", "geoplanet:7.5.2", "geoplanet:7.6.0", "geoplanet:7.8.1", "geoplanet:7.9.0", "geoplanet:7.10.0", "geoplanet:8.0.0", "woeplanet:8.0.0"], "meta:indexed": "2020-08-20T20:49:03.154259", "woe:alias_ENG_V": ["AXK Airport", "AXK"], "meta:updated": "2020-10-14T11:52:00.258504", "woe:hierarchy": {"continent": 24865671, "country": 23425002, "town": 0, "planet": 1, "county": 56190159, "suburb": 0, "state": 20070034, "region": 0, "localadmin": 0}, "woe:timezone_id": 28350806, "woe:hash": "t496c9c77tdn", "woe:centroid": [46.8256, 14.5561], "geom:latitude": 14.5561, "geom:longitude": 46.8256, "geom:hash": "t496c9c77tdn", "woe:latitude": 14.5561, "geom:centroid": [46.8256, 14.5561], "woe:longitude": 46.8256, "woe:repo": "woeplanet-airport-ye", "geom:area": 0.0, "woe:scale": 19}}